[
  {
    "id": "f98d73825cde71da",
    "producer": "notebooklm-research",
    "output": "reports",
    "type": "research.report",
    "format": "markdown",
    "path": "raw/notebooklm-analysis/情感承诺与人际忠诚_Rick_Astley_Never_Gonna_Give_Y_1782406371--dQw4w9WgXcQ-20260626.md",
    "title": "情感承诺与人际忠诚_Rick_Astley_Never_Gonna_Give_Y_1782406371--dQw4w9WgXcQ-20260626.md",
    "size": 4510,
    "mime_type": "application/octet-stream",
    "tags": [
      "wiki-source"
    ],
    "metadata": {},
    "resolution": "context"
  }
]
